oinkoink/__init__.py
oinkoink/board.py
oinkoink/evaluators.py
oinkoink/game.py
oinkoink/grid_search.py
oinkoink/main.py
oinkoink/match.py
oinkoink/mcts.py
oinkoink/player.py
oinkoink/tree.py
oinkoink/utils.py
oinkoink/data/connect4dataset_7ply.pth
oinkoink/data/connect4dataset_8ply.pth
oinkoink/data/example_config.py
oinkoink/data/example_net.pth
oinkoink/neural/__init__.py
oinkoink/neural/config.py
oinkoink/neural/game_pool.py
oinkoink/neural/inference_server.py
oinkoink/neural/stats.py
oinkoink/neural/storage.py
oinkoink/neural/training.py
oinkoink/neural/training_game.py
oinkoink/neural/pytorch/__init__.py
oinkoink/neural/pytorch/data.py
oinkoink/neural/pytorch/model.py
oinkoink-1.0.1.dist-info/LICENSE
oinkoink-1.0.1.dist-info/METADATA
oinkoink-1.0.1.dist-info/WHEEL
oinkoink-1.0.1.dist-info/entry_points.txt
oinkoink-1.0.1.dist-info/top_level.txt
oinkoink-1.0.1.dist-info/RECORD
