Metadata-Version: 2.1
Name: oinkoink
Version: 1.0.1
Summary: A Reinforcement Learning agent plays connect4
Home-page: http://github.com/muff2n/connect4
Author: Muff2n
License: MIT
Platform: UNKNOWN
Classifier: Programming Language :: Python :: 3
Classifier: License :: OSI Approved :: MIT License
Requires-Python: >=3.7
Requires-Dist: anytree
Requires-Dist: matplotlib
Requires-Dist: numpy
Requires-Dist: pandas
Requires-Dist: scipy
Requires-Dist: torch
Requires-Dist: visdom
Provides-Extra: test
Requires-Dist: coverage ; extra == 'test'
